odoo8_addon_password_security-8.0.1.1.2-py2.7-nspkg.pth
odoo8_addon_password_security-8.0.1.1.2.dist-info/DESCRIPTION.rst
odoo8_addon_password_security-8.0.1.1.2.dist-info/METADATA
odoo8_addon_password_security-8.0.1.1.2.dist-info/RECORD
odoo8_addon_password_security-8.0.1.1.2.dist-info/WHEEL
odoo8_addon_password_security-8.0.1.1.2.dist-info/metadata.json
odoo8_addon_password_security-8.0.1.1.2.dist-info/namespace_packages.txt
odoo8_addon_password_security-8.0.1.1.2.dist-info/top_level.txt
odoo_addons/password_security/README.rst
odoo_addons/password_security/__init__.py
odoo_addons/password_security/__openerp__.py
odoo_addons/password_security/exceptions.py
odoo_addons/password_security/controllers/__init__.py
odoo_addons/password_security/controllers/main.py
odoo_addons/password_security/demo/res_users.xml
odoo_addons/password_security/i18n/am.po
odoo_addons/password_security/i18n/ar.po
odoo_addons/password_security/i18n/bg.po
odoo_addons/password_security/i18n/bs.po
odoo_addons/password_security/i18n/ca.po
odoo_addons/password_security/i18n/ca_ES.po
odoo_addons/password_security/i18n/cs.po
odoo_addons/password_security/i18n/da.po
odoo_addons/password_security/i18n/de.po
odoo_addons/password_security/i18n/el_GR.po
odoo_addons/password_security/i18n/en_GB.po
odoo_addons/password_security/i18n/es.po
odoo_addons/password_security/i18n/es_AR.po
odoo_addons/password_security/i18n/es_CL.po
odoo_addons/password_security/i18n/es_CO.po
odoo_addons/password_security/i18n/es_CR.po
odoo_addons/password_security/i18n/es_DO.po
odoo_addons/password_security/i18n/es_EC.po
odoo_addons/password_security/i18n/es_ES.po
odoo_addons/password_security/i18n/es_MX.po
odoo_addons/password_security/i18n/es_PE.po
odoo_addons/password_security/i18n/es_PY.po
odoo_addons/password_security/i18n/es_VE.po
odoo_addons/password_security/i18n/et.po
odoo_addons/password_security/i18n/eu.po
odoo_addons/password_security/i18n/fa.po
odoo_addons/password_security/i18n/fi.po
odoo_addons/password_security/i18n/fr.po
odoo_addons/password_security/i18n/fr_CA.po
odoo_addons/password_security/i18n/fr_CH.po
odoo_addons/password_security/i18n/fr_FR.po
odoo_addons/password_security/i18n/gl.po
odoo_addons/password_security/i18n/gl_ES.po
odoo_addons/password_security/i18n/he.po
odoo_addons/password_security/i18n/hr.po
odoo_addons/password_security/i18n/hr_HR.po
odoo_addons/password_security/i18n/hu.po
